MANIFEST.in
license.txt
setup.py
alembic/env.py
alembic/script.py.mako
alembic/versions/1e0a9d82ddc3_initial_setup.py
alembic/versions/7d1e9dd251c_add_hash_to_user.py
bin/vispa
bin/vispad
conf/cherrypy.ini.sample
conf/logging-rpc.ini.sample
conf/logging.ini.sample
conf/vispa.ini.sample
vispa/__init__.py
vispa/bus.py
vispa/rpc.py
vispa/server.py
vispa/url.py
vispa.egg-info/PKG-INFO
vispa.egg-info/SOURCES.txt
vispa.egg-info/dependency_links.txt
vispa.egg-info/requires.txt
vispa.egg-info/top_level.txt
vispa/controller/__init__.py
vispa/controller/ajax.py
vispa/controller/bus.py
vispa/controller/error.py
vispa/controller/filesystem.py
vispa/controller/filesystem.py.orig
vispa/controller/platform.py
vispa/extensions/__init__.py
vispa/extensions/codeeditor/__init__.py
vispa/extensions/codeeditor/remote/__init__.py
vispa/extensions/codeeditor/static/css/styles.css
vispa/extensions/codeeditor/static/js/editor.js
vispa/extensions/codeeditor/static/js/extension.js
vispa/extensions/demo/__init__.py
vispa/extensions/demo/controller.py
vispa/extensions/demo/remote/__init__.py
vispa/extensions/demo/static/css/styles.css
vispa/extensions/demo/static/js/extension.js
vispa/extensions/dummy/__init__.py
vispa/extensions/dummy/controller.py
vispa/extensions/dummy/remote/__init__.py
vispa/extensions/dummy/static/css/styles.css
vispa/extensions/dummy/static/js/extension.js
vispa/extensions/file/__init__.py
vispa/extensions/file/static/css/base/base.css
vispa/extensions/file/static/css/base/views/symbol/symbol.css
vispa/extensions/file/static/css/base/views/symbol/white_minus.png
vispa/extensions/file/static/css/base/views/symbol/white_plus.png
vispa/extensions/file/static/css/base/views/table/table.css
vispa/extensions/file/static/html/main.html
vispa/extensions/file/static/html/symbol.html
vispa/extensions/file/static/html/table.html
vispa/extensions/file/static/img/c.png
vispa/extensions/file/static/img/cpp.png
vispa/extensions/file/static/img/default.png
vispa/extensions/file/static/img/document-open.png
vispa/extensions/file/static/img/edit-cut.png
vispa/extensions/file/static/img/edit-delete.png
